LICENSE
README.md
pyproject.toml
setup.py
SeoKeywordResearch/__init__.py
SeoKeywordResearch/cli.py
SeoKeywordResearch/seo_keyword_research.py
seo_keyword_research_tool.egg-info/PKG-INFO
seo_keyword_research_tool.egg-info/SOURCES.txt
seo_keyword_research_tool.egg-info/dependency_links.txt
seo_keyword_research_tool.egg-info/entry_points.txt
seo_keyword_research_tool.egg-info/requires.txt
seo_keyword_research_tool.egg-info/top_level.txt