Metadata-Version: 2.1
Name: seo-keyword-research-tool
Version: 0.1.8
Summary: Python SEO keywords suggestion tool. Google Autocomplete, Related Questions and Related Searches.
Home-page: https://github.com/chukhraiartur/seo-keyword-research-tool
Author: Artur Chukhrai
Author-email: chukhraiartur@gmail.com
Maintainer: Artur Chukhrai, Dmitiry Zub
Maintainer-email: chukhraiartur@gmail.com, dimitryzub@gmail.com
License: MIT
Project-URL: Documentation, https://github.com/chukhraiartur/seo-keyword-research-tool
Project-URL: Source, https://github.com/chukhraiartur/seo-keyword-research-tool
Project-URL: Tracker, https://github.com/chukhraiartur/seo-keyword-research-tool/issues
Keywords: google scholar,serpapi,scraper,python,python google scholar,python google scholar api,web scraping,python web scraping,research,google-search-results,cli
Platform: UNKNOWN
Classifier: Development Status :: 3 - Alpha
Classifier: Intended Audience :: Developers
Classifier: Operating System :: Microsoft :: Windows
Classifier: Operating System :: MacOS
Classifier: Operating System :: POSIX :: Linux
Classifier: Topic :: Internet
Classifier: Natural Language :: English
Classifier: Topic :: Utilities
Classifier: Programming Language :: Python :: 3.8
Classifier: Programming Language :: Python :: 3.9
Classifier: Programming Language :: Python :: 3.10
Requires-Python: >=3.8
